{
	"format_version": "1.21.6",
	"credit": "Made with Blockbench",
	"parent": "builtin/entity",
	"texture_size": [32, 32],
	"textures": {
		"particle": "item/texture"
	},
	"display": {
		"thirdperson_righthand": {
			"rotation": [0, -180, 0],
			"translation": [0.75, -5.5, 1.25]
		},
		"thirdperson_lefthand": {
			"rotation": [0, -180, 0],
			"translation": [0.25, -5.5, 2.5]
		},
		"firstperson_righthand": {
			"rotation": [157.8, 1.65, -150.69],
			"translation": [-4.25, -2.25, 2.5],
			"scale": [0.72461, 0.5332, 0.67773]
		},
		"firstperson_lefthand": {
			"rotation": [142.29, -28.26, 174.67],
			"translation": [0.75, -0.75, 2.5],
			"scale": [0.63, 0.48, 0.65]
		},
		"ground": {
			"rotation": [-51, 0, 0],
			"translation": [0, 0, 6.25],
			"scale": [0.69, 0.7, 0.66]
		},
		"gui": {
			"rotation": [75.95, -41.64, 80.59],
			"translation": [7, -6.5, 0],
			"scale": [0.56, 0.59, 0.84]
		},
		"fixed": {
			"rotation": [77.21, -45.14, 79.84],
			"translation": [8, -8.25, 0],
			"scale": [1.45, 0.68, 0.99]
		}
	}
}